gpm/__init__.py
gpm/cli.py
gpm/data.txt
gpm/model.py
gpm/pipeline.py
gpm/vocabulary.py
gpmanager-0.4.0.dist-info/METADATA
gpmanager-0.4.0.dist-info/WHEEL
gpmanager-0.4.0.dist-info/RECORD
